streamlit_get_protocol/__init__.py
streamlit_get_protocol/frontend/index.html
streamlit_get_protocol/frontend/main.js
streamlit_get_protocol/frontend/streamlit-component-lib.js
streamlit_get_protocol-0.1.0.dist-info/LICENSE
streamlit_get_protocol-0.1.0.dist-info/METADATA
streamlit_get_protocol-0.1.0.dist-info/WHEEL
streamlit_get_protocol-0.1.0.dist-info/top_level.txt
streamlit_get_protocol-0.1.0.dist-info/RECORD
