Metadata-Version: 2.1
Name: streamlit-get-protocol
Version: 0.1.0
Summary: Get window.location.protocol
Home-page: https://github.com/phamxtien/streamlit-get-protocol
Author: Pham Xuan Tien
Author-email: phamxtien@gmail.com
License: UNKNOWN
Platform: UNKNOWN
Requires-Python: >=3.9
License-File: LICENSE
Requires-Dist: streamlit (>=1.15)
